{"epoch":1726150809,"data":[{"id":"arbitrum","name":"Arbitrum One","type":"optimistic rollup","stage":"stage 1","layer":"L2","state_validation":{"status":"Fraud proofs (INT)","color":"yellow","score":2},"data_availability":{"status":"On chain","color":"white","score":3},"exit_window":{"status":"2d","color":"red","score":1},"sequencer_failure":{"status":"Self sequence","color":"white","score":3},"proposer_failure":{"status":"Self propose","color":"white","score":3},"tvl":{"val":13530000000.0,"str":"13.53 B","color":"green"},"checkmarks":3,"score":13.5},{"id":"base","name":"Base","type":"optimistic rollup","stage":"stage 0","layer":"L2","state_validation":{"status":"In development","color":"red","score":1},"data_availability":{"status":"On chain","color":"white","score":3},"exit_window":{"status":"None","color":"red","score":1},"sequencer_failure":{"status":"Self sequence","color":"white","score":3},"proposer_failure":{"status":"Cannot withdraw","color":"red","score":1},"tvl":{"val":6090000000.0,"str":"6.09 B","color":"green"},"checkmarks":2,"score":9},{"id":"optimism","name":"OP Mainnet","type":"optimistic rollup","stage":"stage 1","layer":"L2","state_validation":{"status":"Fraud proofs (INT)","color":"white","score":3},"data_availability":{"status":"On chain","color":"white","score":3},"exit_window":{"status":"None","color":"red","score":1},"sequencer_failure":{"status":"Self sequence","color":"white","score":3},"proposer_failure":{"status":"Self propose","color":"white","score":3},"tvl":{"val":5740000000.0,"str":"5.74 B","color":"green"},"checkmarks":4,"score":14.5},{"id":"blast","name":"Blast","type":"optimistic rollup","stage":"stage 0","layer":"L2","state_validation":{"status":"In development","color":"red","score":1},"data_availability":{"status":"On chain","color":"white","score":3},"exit_window":{"status":"None","color":"red","score":1},"sequencer_failure":{"status":"Self sequence","color":"white","score":3},"proposer_failure":{"status":"Cannot withdraw","color":"red","score":1},"tvl":{"val":1470000000.0,"str":"1.47 B","color":"green"},"checkmarks":2,"score":9},{"id":"scroll","name":"Scroll","type":"zk rollup","stage":"stage 0","layer":"L2","state_validation":{"status":"ZK proofs (SN)","color":"white","score":3},"data_availability":{"status":"On chain","color":"white","score":3},"exit_window":{"status":"None","color":"red","score":1},"sequencer_failure":{"status":"No mechanism","color":"red","score":1},"proposer_failure":{"status":"Cannot withdraw","color":"red","score":1},"tvl":{"val":1150000000.0,"str":"1.15 B","color":"green"},"checkmarks":2,"score":9},{"id":"linea","name":"Linea","type":"zk rollup","stage":"stage 0","layer":"L2","state_validation":{"status":"ZK proofs (SN)","color":"white","score":3},"data_availability":{"status":"On chain","color":"white","score":3},"exit_window":{"status":"None","color":"red","score":1},"sequencer_failure":{"status":"No mechanism","color":"red","score":1},"proposer_failure":{"status":"Cannot withdraw","color":"red","score":1},"tvl":{"val":761960000.0,"str":"761.96 M","color":"green"},"checkmarks":2,"score":9},{"id":"starknet","name":"Starknet","type":"zk rollup","stage":"stage 0","layer":"L2","state_validation":{"status":"ZK proofs (ST)","color":"white","score":3},"data_availability":{"status":"On chain (SD)","color":"white","score":3},"exit_window":{"status":"None","color":"red","score":1},"sequencer_failure":{"status":"No mechanism","color":"red","score":1},"proposer_failure":{"status":"Cannot withdraw","color":"red","score":1},"tvl":{"val":609380000.0,"str":"609.38 M","color":"green"},"checkmarks":2,"score":9},{"id":"mode","name":"Mode Network","type":"optimistic rollup","stage":"stage 0","layer":"L2","state_validation":{"status":"In development","color":"red","score":1},"data_availability":{"status":"On chain","color":"white","score":3},"exit_window":{"status":"None","color":"red","score":1},"sequencer_failure":{"status":"Self sequence","color":"white","score":3},"proposer_failure":{"status":"Cannot withdraw","color":"red","score":1},"tvl":{"val":452150000.0,"str":"452.15 M","color":"white"},"checkmarks":2,"score":9},{"id":"dydx","name":"dYdX v3","type":"zk rollup","stage":"stage 1","layer":"L2","state_validation":{"status":"ZK proofs (ST)","color":"white","score":3},"data_availability":{"status":"On chain","color":"white","score":3},"exit_window":{"status":"None","color":"red","score":1},"sequencer_failure":{"status":"Force via L1","color":"white","score":3},"proposer_failure":{"status":"Use escape hatch","color":"white","score":3},"tvl":{"val":197800000.0,"str":"197.80 M","color":"white"},"checkmarks":4,"score":14.5},{"id":"lisk","name":"Lisk","type":"optimistic rollup","stage":"stage 0","layer":"L2","state_validation":{"status":"In development","color":"red","score":1},"data_availability":{"status":"On chain","color":"white","score":3},"exit_window":{"status":"None","color":"red","score":1},"sequencer_failure":{"status":"Self sequence","color":"white","score":3},"proposer_failure":{"status":"Cannot withdraw","color":"red","score":1},"tvl":{"val":127300000.0,"str":"127.30 M","color":"white"},"checkmarks":2,"score":9},{"id":"polygonzkevm","name":"Polygon zkEVM","type":"zk rollup","stage":"stage 0","layer":"L2","state_validation":{"status":"ZK proofs (SN)","color":"white","score":3},"data_availability":{"status":"On chain","color":"white","score":3},"exit_window":{"status":"None","color":"red","score":1},"sequencer_failure":{"status":"No mechanism","color":"red","score":1},"proposer_failure":{"status":"Self propose","color":"white","score":3},"tvl":{"val":102980000.0,"str":"102.98 M","color":"white"},"checkmarks":3,"score":11},{"id":"immutablex","name":"Immutable X","type":"validium","stage":"-","layer":"L2","state_validation":{"status":"ZK proofs (ST)","color":"white","score":3},"data_availability":{"status":"External (DAC)","color":"red","score":1},"exit_window":{"status":"None","color":"red","score":1},"sequencer_failure":{"status":"Force via L1","color":"white","score":3},"proposer_failure":{"status":"Use escape hatch","color":"white","score":3},"tvl":{"val":102340000.0,"str":"102.34 M","color":"white"},"checkmarks":3,"score":11},{"id":"taiko","name":"Taiko","type":"optimistic rollup","stage":"stage 0","layer":"L2","state_validation":{"status":"SGX Proofs","color":"red","score":1},"data_availability":{"status":"On chain","color":"white","score":3},"exit_window":{"status":"None","color":"red","score":1},"sequencer_failure":{"status":"Self sequence","color":"white","score":3},"proposer_failure":{"status":"Self propose","color":"white","score":3},"tvl":{"val":94730000.0,"str":"94.73 M","color":"yellow"},"checkmarks":3,"score":11},{"id":"apex","name":"ApeX","type":"validium","stage":"-","layer":"L2","state_validation":{"status":"ZK proofs (ST)","color":"white","score":3},"data_availability":{"status":"External (DAC)","color":"red","score":1},"exit_window":{"status":"None","color":"red","score":1},"sequencer_failure":{"status":"Force via L1","color":"white","score":3},"proposer_failure":{"status":"Use escape hatch","color":"white","score":3},"tvl":{"val":85870000.0,"str":"85.87 M","color":"yellow"},"checkmarks":3,"score":11},{"id":"bob","name":"BOB","type":"optimistic rollup","stage":"stage 0","layer":"L2","state_validation":{"status":"In development","color":"red","score":1},"data_availability":{"status":"On chain","color":"white","score":3},"exit_window":{"status":"None","color":"red","score":1},"sequencer_failure":{"status":"Self sequence","color":"white","score":3},"proposer_failure":{"status":"Cannot withdraw","color":"red","score":1},"tvl":{"val":83310000.0,"str":"83.31 M","color":"yellow"},"checkmarks":2,"score":9},{"id":"degate3","name":"DeGate V1","type":"zk rollup","stage":"stage 2","layer":"L2","state_validation":{"status":"ZK proofs (SN)","color":"white","score":3},"data_availability":{"status":"On chain","color":"white","score":3},"exit_window":{"status":"30d","color":"white","score":3},"sequencer_failure":{"status":"Force via L1","color":"white","score":3},"proposer_failure":{"status":"Use escape hatch","color":"white","score":3},"tvl":{"val":50510000.0,"str":"50.51 M","color":"yellow"},"checkmarks":5,"score":18},{"id":"zksync-lite","name":"ZKsync Lite","type":"zk rollup","stage":"stage 1","layer":"L2","state_validation":{"status":"ZK proofs (SN)","color":"white","score":3},"data_availability":{"status":"On chain","color":"white","score":3},"exit_window":{"status":"7d","color":"yellow","score":2},"sequencer_failure":{"status":"Force via L1","color":"white","score":3},"proposer_failure":{"status":"Use escape hatch","color":"white","score":3},"tvl":{"val":47100000.0,"str":"47.10 M","color":"yellow"},"checkmarks":4,"score":15.5},{"id":"loopring","name":"Loopring","type":"zk rollup","stage":"stage 0","layer":"L2","state_validation":{"status":"ZK proofs (SN)","color":"white","score":3},"data_availability":{"status":"On chain","color":"white","score":3},"exit_window":{"status":"None","color":"red","score":1},"sequencer_failure":{"status":"Force via L1","color":"white","score":3},"proposer_failure":{"status":"Use escape hatch","color":"white","score":3},"tvl":{"val":44230000.0,"str":"44.23 M","color":"yellow"},"checkmarks":4,"score":13},{"id":"zora","name":"Zora","type":"optimistic rollup","stage":"stage 0","layer":"L2","state_validation":{"status":"In development","color":"red","score":1},"data_availability":{"status":"On chain","color":"white","score":3},"exit_window":{"status":"None","color":"red","score":1},"sequencer_failure":{"status":"Self sequence","color":"white","score":3},"proposer_failure":{"status":"Cannot withdraw","color":"red","score":1},"tvl":{"val":18370000.0,"str":"18.37 M","color":"yellow"},"checkmarks":2,"score":9},{"id":"kroma","name":"Kroma","type":"optimistic rollup","stage":"stage 0","layer":"L2","state_validation":{"status":"Fraud proofs (INT, ZK)","color":"red","score":1},"data_availability":{"status":"On chain","color":"white","score":3},"exit_window":{"status":"None","color":"red","score":1},"sequencer_failure":{"status":"Self sequence","color":"white","score":3},"proposer_failure":{"status":"Self propose","color":"white","score":3},"tvl":{"val":18160000.0,"str":"18.16 M","color":"yellow"},"checkmarks":3,"score":11},{"id":"kinto","name":"Kinto","type":"optimistic rollup","stage":"stage 0","layer":"L2","state_validation":{"status":"Fraud proofs (INT)","color":"red","score":1},"data_availability":{"status":"On chain","color":"white","score":3},"exit_window":{"status":"None","color":"red","score":1},"sequencer_failure":{"status":"Self sequence","color":"white","score":3},"proposer_failure":{"status":"Self propose","color":"white","score":3},"tvl":{"val":17520000.0,"str":"17.52 M","color":"yellow"},"checkmarks":3,"score":11},{"id":"zkfair","name":"ZKFair","type":"validium","stage":"-","layer":"L2","state_validation":{"status":"ZK proofs (SN)","color":"white","score":3},"data_availability":{"status":"External (DAC)","color":"red","score":1},"exit_window":{"status":"None","color":"red","score":1},"sequencer_failure":{"status":"No mechanism","color":"red","score":1},"proposer_failure":{"status":"Self propose","color":"white","score":3},"tvl":{"val":17040000.0,"str":"17.04 M","color":"yellow"},"checkmarks":2,"score":9},{"id":"sorare","name":"Sorare","type":"validium","stage":"-","layer":"L2","state_validation":{"status":"ZK proofs (ST)","color":"white","score":3},"data_availability":{"status":"External (DAC)","color":"red","score":1},"exit_window":{"status":"None","color":"red","score":1},"sequencer_failure":{"status":"Force via L1","color":"white","score":3},"proposer_failure":{"status":"Use escape hatch","color":"white","score":3},"tvl":{"val":16170000.000000002,"str":"16.17 M","color":"yellow"},"checkmarks":3,"score":11},{"id":"paradex","name":"Paradex","type":"zk rollup","stage":"stage 0","layer":"L2","state_validation":{"status":"ZK proofs (ST)","color":"white","score":3},"data_availability":{"status":"On chain (SD)","color":"white","score":3},"exit_window":{"status":"None","color":"red","score":1},"sequencer_failure":{"status":"No mechanism","color":"red","score":1},"proposer_failure":{"status":"Cannot withdraw","color":"red","score":1},"tvl":{"val":15100000.0,"str":"15.10 M","color":"yellow"},"checkmarks":2,"score":9},{"id":"bobanetwork","name":"Boba Network","type":"optimistic rollup","stage":"stage 0","layer":"L2","state_validation":{"status":"In development","color":"red","score":1},"data_availability":{"status":"On chain","color":"white","score":3},"exit_window":{"status":"None","color":"red","score":1},"sequencer_failure":{"status":"Self sequence","color":"white","score":3},"proposer_failure":{"status":"Cannot withdraw","color":"red","score":1},"tvl":{"val":11360000.0,"str":"11.36 M","color":"yellow"},"checkmarks":2,"score":9},{"id":"rhinofi","name":"rhino.fi","type":"validium","stage":"-","layer":"L2","state_validation":{"status":"ZK proofs (ST)","color":"white","score":3},"data_availability":{"status":"External (DAC)","color":"red","score":1},"exit_window":{"status":"None","color":"red","score":1},"sequencer_failure":{"status":"Force via L1","color":"white","score":3},"proposer_failure":{"status":"Use escape hatch","color":"white","score":3},"tvl":{"val":11150000.0,"str":"11.15 M","color":"yellow"},"checkmarks":3,"score":11},{"id":"zkspace","name":"ZKSpace","type":"zk rollup","stage":"stage 0","layer":"L2","state_validation":{"status":"ZK proofs (SN)","color":"white","score":3},"data_availability":{"status":"On chain","color":"white","score":3},"exit_window":{"status":"5d","color":"red","score":1},"sequencer_failure":{"status":"Force via L1","color":"white","score":3},"proposer_failure":{"status":"Use escape hatch","color":"white","score":3},"tvl":{"val":2640000.0,"str":"2.64 M","color":"red"},"checkmarks":4,"score":13},{"id":"mint","name":"Mint","type":"optimistic rollup","stage":"stage 0","layer":"L2","state_validation":{"status":"In development","color":"red","score":1},"data_availability":{"status":"On chain","color":"white","score":3},"exit_window":{"status":"None","color":"red","score":1},"sequencer_failure":{"status":"Self sequence","color":"white","score":3},"proposer_failure":{"status":"Cannot withdraw","color":"red","score":1},"tvl":{"val":1820000.0,"str":"1.82 M","color":"red"},"checkmarks":2,"score":9},{"id":"tanx","name":"tanX","type":"validium","stage":"-","layer":"L2","state_validation":{"status":"ZK proofs (ST)","color":"white","score":3},"data_availability":{"status":"External (DAC)","color":"red","score":1},"exit_window":{"status":"None","color":"red","score":1},"sequencer_failure":{"status":"Force via L1","color":"white","score":3},"proposer_failure":{"status":"Use escape hatch","color":"white","score":3},"tvl":{"val":1320000.0,"str":"1.32 M","color":"red"},"checkmarks":3,"score":11},{"id":"termstructure","name":"Term Structure","type":"zk rollup","stage":"stage 0","layer":"L2","state_validation":{"status":"ZK proofs (SN)","color":"white","score":3},"data_availability":{"status":"On chain","color":"white","score":3},"exit_window":{"status":"None","color":"red","score":1},"sequencer_failure":{"status":"Force via L1","color":"white","score":3},"proposer_failure":{"status":"Use escape hatch","color":"white","score":3},"tvl":{"val":941980.0,"str":"941.98 K","color":"red"},"checkmarks":4,"score":13},{"id":"zircuit","name":"Zircuit","type":"optimistic rollup","stage":"stage 0","layer":"L2","state_validation":{"status":"In development","color":"red","score":1},"data_availability":{"status":"On chain","color":"white","score":3},"exit_window":{"status":"None","color":"red","score":1},"sequencer_failure":{"status":"Self sequence","color":"white","score":3},"proposer_failure":{"status":"Cannot withdraw","color":"red","score":1},"tvl":{"val":670450.0,"str":"670.45 K","color":"red"},"checkmarks":2,"score":9},{"id":"optopia","name":"Optopia","type":"optimistic rollup","stage":"stage 0","layer":"L2","state_validation":{"status":"In development","color":"red","score":1},"data_availability":{"status":"On chain","color":"white","score":3},"exit_window":{"status":"None","color":"red","score":1},"sequencer_failure":{"status":"Self sequence","color":"white","score":3},"proposer_failure":{"status":"Cannot withdraw","color":"red","score":1},"tvl":{"val":529220.0,"str":"529.22 K","color":"red"},"checkmarks":2,"score":9},{"id":"cartesi-honeypot","name":"Honeypot (Cartesi)","type":"optimistic rollup","stage":"stage 0","layer":"L2","state_validation":{"status":"None","color":"red","score":1},"data_availability":{"status":"On chain","color":"white","score":3},"exit_window":{"status":"∞","color":"white","score":3},"sequencer_failure":{"status":"Self sequence","color":"white","score":3},"proposer_failure":{"status":"Cannot withdraw","color":"red","score":1},"tvl":{"val":211270.0,"str":"211.27 K","color":"red"},"checkmarks":3,"score":11},{"id":"metal","name":"Metal","type":"optimistic rollup","stage":"stage 0","layer":"L2","state_validation":{"status":"In development","color":"red","score":1},"data_availability":{"status":"On chain","color":"white","score":3},"exit_window":{"status":"None","color":"red","score":1},"sequencer_failure":{"status":"Self sequence","color":"white","score":3},"proposer_failure":{"status":"Cannot withdraw","color":"red","score":1},"tvl":{"val":154190.0,"str":"154.19 K","color":"red"},"checkmarks":2,"score":9},{"id":"myria","name":"Myria","type":"validium","stage":"-","layer":"L2","state_validation":{"status":"ZK proofs (ST)","color":"white","score":3},"data_availability":{"status":"External (DAC)","color":"red","score":1},"exit_window":{"status":"None","color":"red","score":1},"sequencer_failure":{"status":"Force via L1","color":"white","score":3},"proposer_failure":{"status":"Use escape hatch","color":"white","score":3},"tvl":{"val":130630.0,"str":"130.63 K","color":"red"},"checkmarks":3,"score":11},{"id":"parallel","name":"Parallel","type":"optimistic rollup","stage":"stage 0","layer":"L2","state_validation":{"status":"Fraud proofs (INT)","color":"red","score":1},"data_availability":{"status":"On chain","color":"white","score":3},"exit_window":{"status":"None","color":"red","score":1},"sequencer_failure":{"status":"Self sequence","color":"white","score":3},"proposer_failure":{"status":"Self propose","color":"white","score":3},"tvl":{"val":64860.0,"str":"64.86 K","color":"red"},"checkmarks":3,"score":11},{"id":"patex","name":"Patex Network","type":"optimistic rollup","stage":"in review","layer":"L2","state_validation":{"status":null,"color":null,"score":0},"data_availability":{"status":null,"color":null,"score":0},"exit_window":{"status":null,"color":null,"score":0},"sequencer_failure":{"status":null,"color":null,"score":0},"proposer_failure":{"status":null,"color":null,"score":0},"tvl":{"val":47200.0,"str":"47.20 K","color":"red"},"checkmarks":0,"score":0},{"id":"swan","name":"Swan Chain","type":"optimistic rollup","stage":"stage 0","layer":"L2","state_validation":{"status":"In development","color":"red","score":1},"data_availability":{"status":"On chain","color":"white","score":3},"exit_window":{"status":"None","color":"red","score":1},"sequencer_failure":{"status":"Self sequence","color":"white","score":3},"proposer_failure":{"status":"Cannot withdraw","color":"red","score":1},"tvl":{"val":36860.0,"str":"36.86 K","color":"red"},"checkmarks":2,"score":9},{"id":"lambda","name":"Lambda Chain","type":"optimistic rollup","stage":"stage 0","layer":"L2","state_validation":{"status":"In development","color":"red","score":1},"data_availability":{"status":"On chain","color":"white","score":3},"exit_window":{"status":"None","color":"red","score":1},"sequencer_failure":{"status":"Self sequence","color":"white","score":3},"proposer_failure":{"status":"Cannot withdraw","color":"red","score":1},"tvl":{"val":11770.0,"str":"11.77 K","color":"red"},"checkmarks":2,"score":9},{"id":"fuelv1","name":"Fuel v1","type":"optimistic rollup","stage":"stage 2","layer":"L2","state_validation":{"status":"Fraud proofs (1R)","color":"white","score":3},"data_availability":{"status":"On chain","color":"white","score":3},"exit_window":{"status":"∞","color":"white","score":3},"sequencer_failure":{"status":"Self sequence","color":"white","score":3},"proposer_failure":{"status":"Self propose","color":"white","score":3},"tvl":{"val":607.78,"str":"607.78","color":"red"},"checkmarks":5,"score":18},{"id":"redsonic","name":"RedSonic","type":"validium","stage":"-","layer":"L2","state_validation":{"status":"ZK proofs (ST)","color":"white","score":3},"data_availability":{"status":"External (DAC)","color":"red","score":1},"exit_window":{"status":"None","color":"red","score":1},"sequencer_failure":{"status":"Force via L1","color":"white","score":3},"proposer_failure":{"status":"Use escape hatch","color":"white","score":3},"tvl":{"val":444.92,"str":"444.92","color":"red"},"checkmarks":3,"score":11},{"id":"witness","name":"Witness Chain","type":"validium","stage":"-","layer":"L2","state_validation":{"status":"ZK proofs (SN)","color":"white","score":3},"data_availability":{"status":"External (DAC)","color":"red","score":1},"exit_window":{"status":"None","color":"red","score":1},"sequencer_failure":{"status":"No mechanism","color":"red","score":1},"proposer_failure":{"status":"Self propose","color":"white","score":3},"tvl":{"val":0,"str":"0","color":"red"},"checkmarks":2,"score":9},{"id":"astarzkevm","name":"Astar zkEVM","type":"validium","stage":"-","layer":"L2","state_validation":{"status":"ZK proofs (SN)","color":"white","score":3},"data_availability":{"status":"External (DAC)","color":"red","score":1},"exit_window":{"status":"None","color":"red","score":1},"sequencer_failure":{"status":"No mechanism","color":"red","score":1},"proposer_failure":{"status":"Self propose","color":"white","score":3},"tvl":{"val":0,"str":"0","color":"red"},"checkmarks":2,"score":9},{"id":"xlayer","name":"X Layer","type":"validium","stage":"-","layer":"L2","state_validation":{"status":"ZK proofs (SN)","color":"white","score":3},"data_availability":{"status":"External (DAC)","color":"red","score":1},"exit_window":{"status":"None","color":"red","score":1},"sequencer_failure":{"status":"No mechanism","color":"red","score":1},"proposer_failure":{"status":"Self propose","color":"white","score":3},"tvl":{"val":0,"str":"0","color":"red"},"checkmarks":2,"score":9},{"id":"gpt","name":"GPT Protocol","type":"validium","stage":"-","layer":"L2","state_validation":{"status":"ZK proofs (SN)","color":"white","score":3},"data_availability":{"status":"External (DAC)","color":"red","score":1},"exit_window":{"status":"None","color":"red","score":1},"sequencer_failure":{"status":"No mechanism","color":"red","score":1},"proposer_failure":{"status":"Self propose","color":"white","score":3},"tvl":{"val":0,"str":"0","color":"red"},"checkmarks":2,"score":9},{"id":"wirex","name":"Pay Chain","type":"validium","stage":"-","layer":"L2","state_validation":{"status":"ZK proofs (SN)","color":"white","score":3},"data_availability":{"status":"External (DAC)","color":"red","score":1},"exit_window":{"status":"None","color":"red","score":1},"sequencer_failure":{"status":"No mechanism","color":"red","score":1},"proposer_failure":{"status":"Self propose","color":"white","score":3},"tvl":{"val":0,"str":"0","color":"red"},"checkmarks":2,"score":9},{"id":"silicon","name":"Silicon","type":"validium","stage":"in review","layer":"L2","state_validation":{"status":null,"color":null,"score":0},"data_availability":{"status":null,"color":null,"score":0},"exit_window":{"status":null,"color":null,"score":0},"sequencer_failure":{"status":null,"color":null,"score":0},"proposer_failure":{"status":null,"color":null,"score":0},"tvl":{"val":0,"str":"0","color":"red"},"checkmarks":0,"score":0}]}