{"epoch":1728525439,"data":[{"id":"reya","name":"Reya","type":"optimium","stage":{"status":"n/a","color":"white","score":0},"layer":"L3","state_validation":{"status":"Fraud proofs (INT)","color":"red","score":1},"data_availability":{"status":"External (DAC)","color":"red","score":1},"exit_window":{"status":"None","color":"red","score":1},"sequencer_failure":{"status":"Self sequence","color":"white","score":3},"proposer_failure":{"status":"Self propose","color":"white","score":3},"tvl":{"val":35650000.0,"str":"35.65 M","color":"yellow"},"checkmarks":2,"score":9},{"id":"bugbuster","name":"Bug Buster","type":"optimistic rollup","stage":{"status":"n/a","color":"white","score":0},"layer":"L2","state_validation":{"status":"None","color":"red","score":1},"data_availability":{"status":"Onchain","color":"white","score":3},"exit_window":{"status":"None","color":"red","score":1},"sequencer_failure":{"status":"Self sequence","color":"white","score":3},"proposer_failure":{"status":"Cannot withdraw","color":"red","score":1},"tvl":{"val":501.75,"str":"501.75","color":"red"},"checkmarks":2,"score":9},{"id":"publicgoodsnetwork","name":"Public Goods Network","type":"optimium","stage":{"status":"n/a","color":"white","score":0},"layer":"L3","state_validation":{"status":"None","color":"red","score":1},"data_availability":{"status":"External","color":"red","score":1},"exit_window":{"status":"None","color":"red","score":1},"sequencer_failure":{"status":"Self sequence","color":"white","score":3},"proposer_failure":{"status":"Cannot withdraw","color":"red","score":1},"tvl":{"val":558050.0,"str":"558.05 K","color":"red"},"checkmarks":1,"score":7},{"id":"scroll","name":"Scroll","type":"zk rollup","stage":{"status":"","color":null,"score":0},"layer":"L2","state_validation":{"status":"ZK proofs (SN)","color":"white","score":3},"data_availability":{"status":"Onchain","color":"white","score":3},"exit_window":{"status":"None","color":"red","score":1},"sequencer_failure":{"status":"No mechanism","color":"red","score":1},"proposer_failure":{"status":"Cannot withdraw","color":"red","score":1},"tvl":{"val":1240000000.0,"str":"1.24 B","color":"green"},"checkmarks":2,"score":9},{"id":"zklinknova","name":"zkLink Nova","type":"validium","stage":{"status":"n/a","color":"white","score":0},"layer":"L2","state_validation":{"status":"ZK proofs","color":"white","score":3},"data_availability":{"status":"External","color":"red","score":1},"exit_window":{"status":"None","color":"red","score":1},"sequencer_failure":{"status":"No mechanism","color":"red","score":1},"proposer_failure":{"status":"Cannot withdraw","color":"red","score":1},"tvl":{"val":86830000.0,"str":"86.83 M","color":"yellow"},"checkmarks":1,"score":7},{"id":"superlumio","name":"SuperLumio","type":"optimistic rollup","stage":{"status":"","color":null,"score":0},"layer":"L2","state_validation":{"status":"None","color":"red","score":1},"data_availability":{"status":"Onchain","color":"white","score":3},"exit_window":{"status":"None","color":"red","score":1},"sequencer_failure":{"status":"Self sequence","color":"white","score":3},"proposer_failure":{"status":"Cannot withdraw","color":"red","score":1},"tvl":{"val":214950.0,"str":"214.95 K","color":"red"},"checkmarks":2,"score":9},{"id":"myria","name":"Myria","type":"validium","stage":{"status":"n/a","color":"white","score":0},"layer":"L2","state_validation":{"status":"ZK proofs (ST)","color":"white","score":3},"data_availability":{"status":"External (DAC)","color":"red","score":1},"exit_window":{"status":"None","color":"red","score":1},"sequencer_failure":{"status":"Force via L1","color":"white","score":3},"proposer_failure":{"status":"Use escape hatch","color":"white","score":3},"tvl":{"val":131520.0,"str":"131.52 K","color":"red"},"checkmarks":3,"score":11},{"id":"race","name":"Race Network","type":"optimistic rollup","stage":{"status":"","color":null,"score":0},"layer":"L2","state_validation":{"status":null,"color":null,"score":0},"data_availability":{"status":null,"color":null,"score":0},"exit_window":{"status":null,"color":null,"score":0},"sequencer_failure":{"status":null,"color":null,"score":0},"proposer_failure":{"status":null,"color":null,"score":0},"tvl":{"val":1040.0,"str":"1.04 K","color":"red"},"checkmarks":0,"score":0},{"id":"degate3","name":"DeGate V1","type":"zk rollup","stage":{"status":"","color":null,"score":0},"layer":"L2","state_validation":{"status":"ZK proofs (SN)","color":"white","score":3},"data_availability":{"status":"Onchain","color":"white","score":3},"exit_window":{"status":"30d","color":"white","score":3},"sequencer_failure":{"status":"Force via L1","color":"white","score":3},"proposer_failure":{"status":"Use escape hatch","color":"white","score":3},"tvl":{"val":53290000.0,"str":"53.29 M","color":"yellow"},"checkmarks":5,"score":15},{"id":"bob","name":"BOB","type":"optimistic rollup","stage":{"status":"","color":null,"score":0},"layer":"L2","state_validation":{"status":"None","color":"red","score":1},"data_availability":{"status":"Onchain","color":"white","score":3},"exit_window":{"status":"None","color":"red","score":1},"sequencer_failure":{"status":"Self sequence","color":"white","score":3},"proposer_failure":{"status":"Cannot withdraw","color":"red","score":1},"tvl":{"val":94980000.0,"str":"94.98 M","color":"yellow"},"checkmarks":2,"score":9},{"id":"teva","name":"Teva Chain","type":"zk rollup","stage":{"status":"n/a","color":"white","score":0},"layer":"L2","state_validation":{"status":null,"color":null,"score":0},"data_availability":{"status":null,"color":null,"score":0},"exit_window":{"status":null,"color":null,"score":0},"sequencer_failure":{"status":null,"color":null,"score":0},"proposer_failure":{"status":null,"color":null,"score":0},"tvl":{"val":0,"str":"0","color":"red"},"checkmarks":0,"score":0},{"id":"nova","name":"Arbitrum Nova","type":"optimium","stage":{"status":"n/a","color":"white","score":0},"layer":"L3","state_validation":{"status":"Fraud proofs (INT)","color":"yellow","score":2},"data_availability":{"status":"External (DAC)","color":"yellow","score":2},"exit_window":{"status":"2d","color":"red","score":1},"sequencer_failure":{"status":"Self sequence","color":"white","score":3},"proposer_failure":{"status":"Self propose","color":"white","score":3},"tvl":{"val":33790000.0,"str":"33.79 M","color":"yellow"},"checkmarks":2,"score":11},{"id":"termstructure","name":"Term Structure","type":"zk rollup","stage":{"status":"","color":null,"score":0},"layer":"L2","state_validation":{"status":"ZK proofs (SN)","color":"white","score":3},"data_availability":{"status":"Onchain","color":"white","score":3},"exit_window":{"status":"None","color":"red","score":1},"sequencer_failure":{"status":"Force via L1","color":"white","score":3},"proposer_failure":{"status":"Use escape hatch","color":"white","score":3},"tvl":{"val":1000000.0,"str":"1.00 M","color":"red"},"checkmarks":4,"score":13},{"id":"dydx","name":"dYdX v3","type":"zk rollup","stage":{"status":"","color":null,"score":0},"layer":"L2","state_validation":{"status":"ZK proofs (ST)","color":"white","score":3},"data_availability":{"status":"Onchain","color":"white","score":3},"exit_window":{"status":"None","color":"red","score":1},"sequencer_failure":{"status":"Force via L1","color":"white","score":3},"proposer_failure":{"status":"Use escape hatch","color":"white","score":3},"tvl":{"val":140800000.0,"str":"140.80 M","color":"white"},"checkmarks":4,"score":13},{"id":"cheese","name":"CheeseChain","type":"optimium","stage":{"status":"n/a","color":"white","score":0},"layer":"L3","state_validation":{"status":null,"color":null,"score":0},"data_availability":{"status":null,"color":null,"score":0},"exit_window":{"status":null,"color":null,"score":0},"sequencer_failure":{"status":null,"color":null,"score":0},"proposer_failure":{"status":null,"color":null,"score":0},"tvl":{"val":277840.0,"str":"277.84 K","color":"red"},"checkmarks":0,"score":0},{"id":"galxegravity","name":"Gravity","type":"optimium","stage":{"status":"n/a","color":"white","score":0},"layer":"L3","state_validation":{"status":"Fraud proofs (INT)","color":"red","score":1},"data_availability":{"status":"External (DAC)","color":"red","score":1},"exit_window":{"status":"None","color":"red","score":1},"sequencer_failure":{"status":"Self sequence","color":"white","score":3},"proposer_failure":{"status":"Self propose","color":"white","score":3},"tvl":{"val":144300000.0,"str":"144.30 M","color":"white"},"checkmarks":2,"score":9},{"id":"stack","name":"Stack","type":"optimium","stage":{"status":"n/a","color":"white","score":0},"layer":"L3","state_validation":{"status":"None","color":"red","score":1},"data_availability":{"status":"External","color":"red","score":1},"exit_window":{"status":"None","color":"red","score":1},"sequencer_failure":{"status":"Self sequence","color":"white","score":3},"proposer_failure":{"status":"Cannot withdraw","color":"red","score":1},"tvl":{"val":2670.0,"str":"2.67 K","color":"red"},"checkmarks":1,"score":7},{"id":"mint","name":"Mint","type":"optimistic rollup","stage":{"status":"","color":null,"score":0},"layer":"L2","state_validation":{"status":"None","color":"red","score":1},"data_availability":{"status":"Onchain","color":"white","score":3},"exit_window":{"status":"None","color":"red","score":1},"sequencer_failure":{"status":"Self sequence","color":"white","score":3},"proposer_failure":{"status":"Cannot withdraw","color":"red","score":1},"tvl":{"val":2230000.0,"str":"2.23 M","color":"red"},"checkmarks":2,"score":9},{"id":"cyber","name":"Cyber","type":"optimium","stage":{"status":"n/a","color":"white","score":0},"layer":"L3","state_validation":{"status":"None","color":"red","score":1},"data_availability":{"status":"External","color":"red","score":1},"exit_window":{"status":"None","color":"red","score":1},"sequencer_failure":{"status":"Self sequence","color":"white","score":3},"proposer_failure":{"status":"Cannot withdraw","color":"red","score":1},"tvl":{"val":21620000.0,"str":"21.62 M","color":"yellow"},"checkmarks":1,"score":7},{"id":"sorare","name":"Sorare","type":"validium","stage":{"status":"n/a","color":"white","score":0},"layer":"L2","state_validation":{"status":"ZK proofs (ST)","color":"white","score":3},"data_availability":{"status":"External (DAC)","color":"red","score":1},"exit_window":{"status":"None","color":"red","score":1},"sequencer_failure":{"status":"Force via L1","color":"white","score":3},"proposer_failure":{"status":"Use escape hatch","color":"white","score":3},"tvl":{"val":17570000.0,"str":"17.57 M","color":"yellow"},"checkmarks":3,"score":11},{"id":"metis","name":"Metis Andromeda","type":"optimium","stage":{"status":"n/a","color":"white","score":0},"layer":"L3","state_validation":{"status":"None","color":"red","score":1},"data_availability":{"status":"External (MEMO)","color":"red","score":1},"exit_window":{"status":"None","color":"red","score":1},"sequencer_failure":{"status":"Enqueue via L1","color":"yellow","score":2},"proposer_failure":{"status":"Cannot withdraw","color":"red","score":1},"tvl":{"val":231860000.0,"str":"231.86 M","color":"white"},"checkmarks":0,"score":6},{"id":"mantapacific","name":"Manta Pacific","type":"optimium","stage":{"status":"n/a","color":"white","score":0},"layer":"L3","state_validation":{"status":"None","color":"red","score":1},"data_availability":{"status":"External","color":"red","score":1},"exit_window":{"status":"None","color":"red","score":1},"sequencer_failure":{"status":"Self sequence","color":"white","score":3},"proposer_failure":{"status":"Cannot withdraw","color":"red","score":1},"tvl":{"val":492680000.0,"str":"492.68 M","color":"white"},"checkmarks":1,"score":7},{"id":"real","name":"Re.al","type":"optimium","stage":{"status":"n/a","color":"white","score":0},"layer":"L3","state_validation":{"status":"Fraud proofs (INT)","color":"red","score":1},"data_availability":{"status":"External (DAC)","color":"red","score":1},"exit_window":{"status":"None","color":"red","score":1},"sequencer_failure":{"status":"Self sequence","color":"white","score":3},"proposer_failure":{"status":"Self propose","color":"white","score":3},"tvl":{"val":81810000.0,"str":"81.81 M","color":"yellow"},"checkmarks":2,"score":9},{"id":"lisk","name":"Lisk","type":"optimistic rollup","stage":{"status":"","color":null,"score":0},"layer":"L2","state_validation":{"status":"None","color":"red","score":1},"data_availability":{"status":"Onchain","color":"white","score":3},"exit_window":{"status":"None","color":"red","score":1},"sequencer_failure":{"status":"Self sequence","color":"white","score":3},"proposer_failure":{"status":"Cannot withdraw","color":"red","score":1},"tvl":{"val":131900000.0,"str":"131.90 M","color":"white"},"checkmarks":2,"score":9},{"id":"popapex","name":"Proof of Play Apex","type":"optimium","stage":{"status":"n/a","color":"white","score":0},"layer":"L3","state_validation":{"status":"Fraud proofs (INT)","color":"red","score":1},"data_availability":{"status":"External (DAC)","color":"red","score":1},"exit_window":{"status":"None","color":"red","score":1},"sequencer_failure":{"status":"Self sequence","color":"white","score":3},"proposer_failure":{"status":"Self propose","color":"white","score":3},"tvl":{"val":683080.0,"str":"683.08 K","color":"red"},"checkmarks":2,"score":9},{"id":"fraxtal","name":"Fraxtal","type":"optimium","stage":{"status":"n/a","color":"white","score":0},"layer":"L3","state_validation":{"status":"None","color":"red","score":1},"data_availability":{"status":"External","color":"red","score":1},"exit_window":{"status":"None","color":"red","score":1},"sequencer_failure":{"status":"Self sequence","color":"white","score":3},"proposer_failure":{"status":"Cannot withdraw","color":"red","score":1},"tvl":{"val":159540000.0,"str":"159.54 M","color":"white"},"checkmarks":1,"score":7},{"id":"base","name":"Base","type":"optimistic rollup","stage":{"status":"","color":null,"score":0},"layer":"L2","state_validation":{"status":"None","color":"red","score":1},"data_availability":{"status":"Onchain","color":"white","score":3},"exit_window":{"status":"None","color":"red","score":1},"sequencer_failure":{"status":"Self sequence","color":"white","score":3},"proposer_failure":{"status":"Cannot withdraw","color":"red","score":1},"tvl":{"val":7190000000.0,"str":"7.19 B","color":"green"},"checkmarks":2,"score":9},{"id":"cronoszkevm","name":"Cronos zkEVM","type":"validium","stage":{"status":"n/a","color":"white","score":0},"layer":"L2","state_validation":{"status":"ZK proofs","color":"white","score":3},"data_availability":{"status":"External","color":"red","score":1},"exit_window":{"status":"None","color":"red","score":1},"sequencer_failure":{"status":"Enqueue via L1","color":"yellow","score":2},"proposer_failure":{"status":"Cannot withdraw","color":"yellow","score":2},"tvl":{"val":24490000.0,"str":"24.49 M","color":"yellow"},"checkmarks":1,"score":9},{"id":"alienx","name":"AlienX","type":"optimium","stage":{"status":"","color":null,"score":0},"layer":"L3","state_validation":{"status":null,"color":null,"score":0},"data_availability":{"status":null,"color":null,"score":0},"exit_window":{"status":null,"color":null,"score":0},"sequencer_failure":{"status":null,"color":null,"score":0},"proposer_failure":{"status":null,"color":null,"score":0},"tvl":{"val":810910.0,"str":"810.91 K","color":"red"},"checkmarks":0,"score":0},{"id":"taiko","name":"Taiko","type":"optimistic rollup","stage":{"status":"","color":null,"score":0},"layer":"L2","state_validation":{"status":"SGX Proofs","color":"red","score":1},"data_availability":{"status":"Onchain","color":"white","score":3},"exit_window":{"status":"None","color":"red","score":1},"sequencer_failure":{"status":"Self sequence","color":"white","score":3},"proposer_failure":{"status":"Self propose","color":"white","score":3},"tvl":{"val":94670000.0,"str":"94.67 M","color":"yellow"},"checkmarks":3,"score":11},{"id":"winr","name":"WINR","type":"optimium","stage":{"status":"n/a","color":"white","score":0},"layer":"L3","state_validation":{"status":null,"color":null,"score":0},"data_availability":{"status":null,"color":null,"score":0},"exit_window":{"status":null,"color":null,"score":0},"sequencer_failure":{"status":null,"color":null,"score":0},"proposer_failure":{"status":null,"color":null,"score":0},"tvl":{"val":4120000.0,"str":"4.12 M","color":"red"},"checkmarks":0,"score":0},{"id":"wirex","name":"Pay Chain","type":"validium","stage":{"status":"n/a","color":"white","score":0},"layer":"L2","state_validation":{"status":"ZK proofs (SN)","color":"white","score":3},"data_availability":{"status":"External (DAC)","color":"red","score":1},"exit_window":{"status":"None","color":"red","score":1},"sequencer_failure":{"status":"No mechanism","color":"red","score":1},"proposer_failure":{"status":"Self propose","color":"white","score":3},"tvl":{"val":4910.0,"str":"4.91 K","color":"red"},"checkmarks":2,"score":9},{"id":"popboss","name":"Proof of Play Boss","type":"optimium","stage":{"status":"n/a","color":"white","score":0},"layer":"L3","state_validation":{"status":"Fraud proofs (INT)","color":"red","score":1},"data_availability":{"status":"External (DAC)","color":"red","score":1},"exit_window":{"status":"None","color":"red","score":1},"sequencer_failure":{"status":"Self sequence","color":"white","score":3},"proposer_failure":{"status":"Self propose","color":"white","score":3},"tvl":{"val":114950.0,"str":"114.95 K","color":"red"},"checkmarks":2,"score":9},{"id":"lambda","name":"Lambda Chain","type":"optimistic rollup","stage":{"status":"","color":null,"score":0},"layer":"L2","state_validation":{"status":"None","color":"red","score":1},"data_availability":{"status":"Onchain","color":"white","score":3},"exit_window":{"status":"None","color":"red","score":1},"sequencer_failure":{"status":"Self sequence","color":"white","score":3},"proposer_failure":{"status":"Cannot withdraw","color":"red","score":1},"tvl":{"val":11960.0,"str":"11.96 K","color":"red"},"checkmarks":2,"score":9},{"id":"deri","name":"Deri","type":"optimistic rollup","stage":{"status":"n/a","color":"white","score":0},"layer":"L2","state_validation":{"status":"Fraud proofs (INT)","color":"red","score":1},"data_availability":{"status":"Onchain","color":"white","score":3},"exit_window":{"status":"None","color":"red","score":1},"sequencer_failure":{"status":"Self sequence","color":"white","score":3},"proposer_failure":{"status":"Self propose","color":"white","score":3},"tvl":{"val":13510.0,"str":"13.51 K","color":"red"},"checkmarks":3,"score":11},{"id":"muster","name":"Muster","type":"optimium","stage":{"status":"n/a","color":"white","score":0},"layer":"L3","state_validation":{"status":null,"color":null,"score":0},"data_availability":{"status":null,"color":null,"score":0},"exit_window":{"status":null,"color":null,"score":0},"sequencer_failure":{"status":null,"color":null,"score":0},"proposer_failure":{"status":null,"color":null,"score":0},"tvl":{"val":0,"str":"0","color":"red"},"checkmarks":0,"score":0},{"id":"polynomial","name":"Polynomial","type":"optimistic rollup","stage":{"status":"","color":null,"score":0},"layer":"L2","state_validation":{"status":"None","color":"red","score":1},"data_availability":{"status":"Onchain","color":"white","score":3},"exit_window":{"status":"None","color":"red","score":1},"sequencer_failure":{"status":"Self sequence","color":"white","score":3},"proposer_failure":{"status":"Cannot withdraw","color":"red","score":1},"tvl":{"val":30410.0,"str":"30.41 K","color":"red"},"checkmarks":2,"score":9},{"id":"molten","name":"Molten Network","type":"optimium","stage":{"status":"n/a","color":"white","score":0},"layer":"L3","state_validation":{"status":"Fraud proofs (INT)","color":"red","score":1},"data_availability":{"status":"External (DAC)","color":"red","score":1},"exit_window":{"status":"None","color":"red","score":1},"sequencer_failure":{"status":"Self sequence","color":"white","score":3},"proposer_failure":{"status":"Self propose","color":"white","score":3},"tvl":{"val":54860.0,"str":"54.86 K","color":"red"},"checkmarks":2,"score":9},{"id":"kinto","name":"Kinto","type":"optimistic rollup","stage":{"status":"","color":null,"score":0},"layer":"L2","state_validation":{"status":"Fraud proofs (INT)","color":"red","score":1},"data_availability":{"status":"Onchain","color":"white","score":3},"exit_window":{"status":"None","color":"red","score":1},"sequencer_failure":{"status":"Self sequence","color":"white","score":3},"proposer_failure":{"status":"Self propose","color":"white","score":3},"tvl":{"val":34130000.0,"str":"34.13 M","color":"yellow"},"checkmarks":3,"score":11},{"id":"redstone","name":"Redstone","type":"optimium","stage":{"status":"n/a","color":"white","score":0},"layer":"L3","state_validation":{"status":"None","color":"red","score":1},"data_availability":{"status":"External","color":"red","score":1},"exit_window":{"status":"None","color":"red","score":1},"sequencer_failure":{"status":"Self sequence","color":"white","score":3},"proposer_failure":{"status":"Cannot withdraw","color":"red","score":1},"tvl":{"val":1490000.0,"str":"1.49 M","color":"red"},"checkmarks":1,"score":7},{"id":"clique","name":"Clique","type":"optimium","stage":{"status":"n/a","color":"white","score":0},"layer":"L3","state_validation":{"status":null,"color":null,"score":0},"data_availability":{"status":null,"color":null,"score":0},"exit_window":{"status":null,"color":null,"score":0},"sequencer_failure":{"status":null,"color":null,"score":0},"proposer_failure":{"status":null,"color":null,"score":0},"tvl":{"val":1350.0,"str":"1.35 K","color":"red"},"checkmarks":0,"score":0},{"id":"dodochain","name":"DODOchain","type":"optimium","stage":{"status":"n/a","color":"white","score":0},"layer":"L3","state_validation":{"status":null,"color":null,"score":0},"data_availability":{"status":null,"color":null,"score":0},"exit_window":{"status":null,"color":null,"score":0},"sequencer_failure":{"status":null,"color":null,"score":0},"proposer_failure":{"status":null,"color":null,"score":0},"tvl":{"val":0,"str":"0","color":"red"},"checkmarks":0,"score":0},{"id":"thebinaryholdings","name":"The Binary Holdings","type":"optimistic rollup","stage":{"status":"","color":null,"score":0},"layer":"L2","state_validation":{"status":"None","color":"red","score":1},"data_availability":{"status":"Onchain","color":"white","score":3},"exit_window":{"status":"None","color":"red","score":1},"sequencer_failure":{"status":"Self sequence","color":"white","score":3},"proposer_failure":{"status":"Cannot withdraw","color":"red","score":1},"tvl":{"val":0,"str":"0","color":"red"},"checkmarks":2,"score":9},{"id":"degen","name":"Degen Chain","type":"optimium","stage":{"status":"n/a","color":"white","score":0},"layer":"L3","state_validation":{"status":"None","color":"red","score":1},"data_availability":{"status":"External (DAC)","color":"red","score":1},"exit_window":{"status":"None","color":"red","score":1},"sequencer_failure":{"status":"Self sequence","color":"white","score":3},"proposer_failure":{"status":"Cannot withdraw","color":"red","score":1},"tvl":{"val":5060000.0,"str":"5.06 M","color":"yellow"},"checkmarks":1,"score":7},{"id":"zksync-lite","name":"ZKsync Lite","type":"zk rollup","stage":{"status":"","color":null,"score":0},"layer":"L2","state_validation":{"status":"ZK proofs (SN)","color":"white","score":3},"data_availability":{"status":"Onchain","color":"white","score":3},"exit_window":{"status":"7d","color":"yellow","score":2},"sequencer_failure":{"status":"Force via L1","color":"white","score":3},"proposer_failure":{"status":"Use escape hatch","color":"white","score":3},"tvl":{"val":47220000.0,"str":"47.22 M","color":"yellow"},"checkmarks":4,"score":14},{"id":"aleph-zero","name":"Aleph Zero EVM","type":"optimium","stage":{"status":"","color":null,"score":0},"layer":"L3","state_validation":{"status":null,"color":null,"score":0},"data_availability":{"status":null,"color":null,"score":0},"exit_window":{"status":null,"color":null,"score":0},"sequencer_failure":{"status":null,"color":null,"score":0},"proposer_failure":{"status":null,"color":null,"score":0},"tvl":{"val":39880.0,"str":"39.88 K","color":"red"},"checkmarks":0,"score":0},{"id":"mantle","name":"Mantle","type":"optimium","stage":{"status":"n/a","color":"white","score":0},"layer":"L3","state_validation":{"status":"None","color":"red","score":1},"data_availability":{"status":"External","color":"red","score":1},"exit_window":{"status":"None","color":"red","score":1},"sequencer_failure":{"status":"Self sequence","color":"white","score":3},"proposer_failure":{"status":"Cannot withdraw","color":"red","score":1},"tvl":{"val":1330000000.0,"str":"1.33 B","color":"green"},"checkmarks":1,"score":7},{"id":"loopring","name":"Loopring","type":"zk rollup","stage":{"status":"","color":null,"score":0},"layer":"L2","state_validation":{"status":"ZK proofs (SN)","color":"white","score":3},"data_availability":{"status":"Onchain","color":"white","score":3},"exit_window":{"status":"None","color":"red","score":1},"sequencer_failure":{"status":"Force via L1","color":"white","score":3},"proposer_failure":{"status":"Use escape hatch","color":"white","score":3},"tvl":{"val":42750000.0,"str":"42.75 M","color":"yellow"},"checkmarks":4,"score":13},{"id":"parallel","name":"Parallel","type":"optimistic rollup","stage":{"status":"","color":null,"score":0},"layer":"L2","state_validation":{"status":"Fraud proofs (INT)","color":"red","score":1},"data_availability":{"status":"Onchain","color":"white","score":3},"exit_window":{"status":"None","color":"red","score":1},"sequencer_failure":{"status":"Self sequence","color":"white","score":3},"proposer_failure":{"status":"Self propose","color":"white","score":3},"tvl":{"val":62810.0,"str":"62.81 K","color":"red"},"checkmarks":3,"score":11},{"id":"playblock","name":"PlayBlock","type":"optimium","stage":{"status":"n/a","color":"white","score":0},"layer":"L3","state_validation":{"status":"Fraud proofs (INT)","color":"red","score":1},"data_availability":{"status":"External (DAC)","color":"red","score":1},"exit_window":{"status":"None","color":"red","score":1},"sequencer_failure":{"status":"Self sequence","color":"white","score":3},"proposer_failure":{"status":"Self propose","color":"white","score":3},"tvl":{"val":0,"str":"0","color":"red"},"checkmarks":2,"score":9},{"id":"starknet","name":"Starknet","type":"zk rollup","stage":{"status":"","color":null,"score":0},"layer":"L2","state_validation":{"status":"ZK proofs (ST)","color":"white","score":3},"data_availability":{"status":"Onchain (SD)","color":"white","score":3},"exit_window":{"status":"None","color":"red","score":1},"sequencer_failure":{"status":"No mechanism","color":"red","score":1},"proposer_failure":{"status":"Cannot withdraw","color":"red","score":1},"tvl":{"val":602970000.0,"str":"602.97 M","color":"green"},"checkmarks":2,"score":9},{"id":"linea","name":"Linea","type":"zk rollup","stage":{"status":"","color":null,"score":0},"layer":"L2","state_validation":{"status":"ZK proofs (SN)","color":"white","score":3},"data_availability":{"status":"Onchain","color":"white","score":3},"exit_window":{"status":"None","color":"red","score":1},"sequencer_failure":{"status":"No mechanism","color":"red","score":1},"proposer_failure":{"status":"Cannot withdraw","color":"red","score":1},"tvl":{"val":709860000.0,"str":"709.86 M","color":"green"},"checkmarks":2,"score":9},{"id":"rss3","name":"RSS3 Value Sublayer","type":"optimium","stage":{"status":"n/a","color":"white","score":0},"layer":"L3","state_validation":{"status":"None","color":"red","score":1},"data_availability":{"status":"External","color":"red","score":1},"exit_window":{"status":"None","color":"red","score":1},"sequencer_failure":{"status":"Self sequence","color":"white","score":3},"proposer_failure":{"status":"Cannot withdraw","color":"red","score":1},"tvl":{"val":64650000.00000001,"str":"64.65 M","color":"yellow"},"checkmarks":1,"score":7},{"id":"witness","name":"Witness Chain","type":"validium","stage":{"status":"n/a","color":"white","score":0},"layer":"L2","state_validation":{"status":"ZK proofs (SN)","color":"white","score":3},"data_availability":{"status":"External (DAC)","color":"red","score":1},"exit_window":{"status":"None","color":"red","score":1},"sequencer_failure":{"status":"No mechanism","color":"red","score":1},"proposer_failure":{"status":"Self propose","color":"white","score":3},"tvl":{"val":0,"str":"0","color":"red"},"checkmarks":2,"score":9},{"id":"astarzkevm","name":"Astar zkEVM","type":"validium","stage":{"status":"n/a","color":"white","score":0},"layer":"L2","state_validation":{"status":"ZK proofs (SN)","color":"white","score":3},"data_availability":{"status":"External (DAC)","color":"red","score":1},"exit_window":{"status":"None","color":"red","score":1},"sequencer_failure":{"status":"No mechanism","color":"red","score":1},"proposer_failure":{"status":"Self propose","color":"white","score":3},"tvl":{"val":3740000.0,"str":"3.74 M","color":"red"},"checkmarks":2,"score":9},{"id":"xterio","name":"Xterio Chain","type":"optimium","stage":{"status":"n/a","color":"white","score":0},"layer":"L3","state_validation":{"status":"None","color":"red","score":1},"data_availability":{"status":"External","color":"red","score":1},"exit_window":{"status":"None","color":"red","score":1},"sequencer_failure":{"status":"Self sequence","color":"white","score":3},"proposer_failure":{"status":"Cannot withdraw","color":"red","score":1},"tvl":{"val":17680.0,"str":"17.68 K","color":"red"},"checkmarks":1,"score":7},{"id":"orderly","name":"Orderly Network","type":"optimium","stage":{"status":"n/a","color":"white","score":0},"layer":"L3","state_validation":{"status":"None","color":"red","score":1},"data_availability":{"status":"External","color":"red","score":1},"exit_window":{"status":"None","color":"red","score":1},"sequencer_failure":{"status":"Self sequence","color":"white","score":3},"proposer_failure":{"status":"Cannot withdraw","color":"red","score":1},"tvl":{"val":18110000.0,"str":"18.11 M","color":"yellow"},"checkmarks":1,"score":7},{"id":"rari","name":"RARI Chain","type":"optimium","stage":{"status":"n/a","color":"white","score":0},"layer":"L3","state_validation":{"status":"Fraud proofs (INT)","color":"red","score":1},"data_availability":{"status":"External (DAC)","color":"red","score":1},"exit_window":{"status":"None","color":"red","score":1},"sequencer_failure":{"status":"Self sequence","color":"white","score":3},"proposer_failure":{"status":"Self propose","color":"white","score":3},"tvl":{"val":437220.0,"str":"437.22 K","color":"red"},"checkmarks":2,"score":9},{"id":"xchain","name":"XCHAIN","type":"optimium","stage":{"status":"","color":null,"score":0},"layer":"L3","state_validation":{"status":null,"color":null,"score":0},"data_availability":{"status":null,"color":null,"score":0},"exit_window":{"status":null,"color":null,"score":0},"sequencer_failure":{"status":null,"color":null,"score":0},"proposer_failure":{"status":null,"color":null,"score":0},"tvl":{"val":1140000.0,"str":"1.14 M","color":"red"},"checkmarks":0,"score":0},{"id":"polygonzkevm","name":"Polygon zkEVM","type":"zk rollup","stage":{"status":"","color":null,"score":0},"layer":"L2","state_validation":{"status":"ZK proofs (SN)","color":"white","score":3},"data_availability":{"status":"Onchain","color":"white","score":3},"exit_window":{"status":"None","color":"red","score":1},"sequencer_failure":{"status":"No mechanism","color":"red","score":1},"proposer_failure":{"status":"Self propose","color":"white","score":3},"tvl":{"val":69000000.0,"str":"69.00 M","color":"yellow"},"checkmarks":3,"score":11},{"id":"ebichain","name":"Ebi Chain","type":"optimium","stage":{"status":"","color":null,"score":0},"layer":"L3","state_validation":{"status":null,"color":null,"score":0},"data_availability":{"status":null,"color":null,"score":0},"exit_window":{"status":null,"color":null,"score":0},"sequencer_failure":{"status":null,"color":null,"score":0},"proposer_failure":{"status":null,"color":null,"score":0},"tvl":{"val":188470.0,"str":"188.47 K","color":"red"},"checkmarks":0,"score":0},{"id":"immutablex","name":"Immutable X","type":"validium","stage":{"status":"n/a","color":"white","score":0},"layer":"L2","state_validation":{"status":"ZK proofs (ST)","color":"white","score":3},"data_availability":{"status":"External (DAC)","color":"red","score":1},"exit_window":{"status":"None","color":"red","score":1},"sequencer_failure":{"status":"Force via L1","color":"white","score":3},"proposer_failure":{"status":"Use escape hatch","color":"white","score":3},"tvl":{"val":104750000.0,"str":"104.75 M","color":"white"},"checkmarks":3,"score":11},{"id":"optopia","name":"Optopia","type":"optimistic rollup","stage":{"status":"","color":null,"score":0},"layer":"L2","state_validation":{"status":"None","color":"red","score":1},"data_availability":{"status":"Onchain","color":"white","score":3},"exit_window":{"status":"None","color":"red","score":1},"sequencer_failure":{"status":"Self sequence","color":"white","score":3},"proposer_failure":{"status":"Cannot withdraw","color":"red","score":1},"tvl":{"val":508770.0,"str":"508.77 K","color":"red"},"checkmarks":2,"score":9},{"id":"xlayer","name":"X Layer","type":"validium","stage":{"status":"n/a","color":"white","score":0},"layer":"L2","state_validation":{"status":"ZK proofs (SN)","color":"white","score":3},"data_availability":{"status":"External (DAC)","color":"red","score":1},"exit_window":{"status":"None","color":"red","score":1},"sequencer_failure":{"status":"No mechanism","color":"red","score":1},"proposer_failure":{"status":"Self propose","color":"white","score":3},"tvl":{"val":28910000.0,"str":"28.91 M","color":"yellow"},"checkmarks":2,"score":9},{"id":"syndicateframe","name":"Syndicate Frame Chain","type":"optimistic rollup","stage":{"status":"n/a","color":"white","score":0},"layer":"L2","state_validation":{"status":"None","color":"red","score":1},"data_availability":{"status":"Onchain","color":"white","score":3},"exit_window":{"status":"None","color":"red","score":1},"sequencer_failure":{"status":"Self sequence","color":"white","score":3},"proposer_failure":{"status":"Cannot withdraw","color":"red","score":1},"tvl":{"val":15190.0,"str":"15.19 K","color":"red"},"checkmarks":2,"score":9},{"id":"aevo","name":"Aevo","type":"optimium","stage":{"status":"n/a","color":"white","score":0},"layer":"L3","state_validation":{"status":"None","color":"red","score":1},"data_availability":{"status":"External","color":"red","score":1},"exit_window":{"status":"None","color":"red","score":1},"sequencer_failure":{"status":"Self sequence","color":"white","score":3},"proposer_failure":{"status":"Cannot withdraw","color":"red","score":1},"tvl":{"val":47360000.0,"str":"47.36 M","color":"yellow"},"checkmarks":1,"score":7},{"id":"rhinofi","name":"rhino.fi","type":"validium","stage":{"status":"n/a","color":"white","score":0},"layer":"L2","state_validation":{"status":"ZK proofs (ST)","color":"white","score":3},"data_availability":{"status":"External (DAC)","color":"red","score":1},"exit_window":{"status":"None","color":"red","score":1},"sequencer_failure":{"status":"Force via L1","color":"white","score":3},"proposer_failure":{"status":"Use escape hatch","color":"white","score":3},"tvl":{"val":11320000.0,"str":"11.32 M","color":"yellow"},"checkmarks":3,"score":11},{"id":"paradex","name":"Paradex","type":"zk rollup","stage":{"status":"","color":null,"score":0},"layer":"L2","state_validation":{"status":"ZK proofs (ST)","color":"white","score":3},"data_availability":{"status":"Onchain (SD)","color":"white","score":3},"exit_window":{"status":"None","color":"red","score":1},"sequencer_failure":{"status":"No mechanism","color":"red","score":1},"proposer_failure":{"status":"Cannot withdraw","color":"red","score":1},"tvl":{"val":14370000.0,"str":"14.37 M","color":"yellow"},"checkmarks":2,"score":9},{"id":"l3x","name":"L3X","type":"optimium","stage":{"status":"n/a","color":"white","score":0},"layer":"L3","state_validation":{"status":"Fraud proofs (INT)","color":"red","score":1},"data_availability":{"status":"External (DAC)","color":"red","score":1},"exit_window":{"status":"None","color":"red","score":1},"sequencer_failure":{"status":"Self sequence","color":"white","score":3},"proposer_failure":{"status":"Self propose","color":"white","score":3},"tvl":{"val":5310.0,"str":"5.31 K","color":"red"},"checkmarks":2,"score":9},{"id":"zksync-era","name":"ZKsync Era","type":"zk rollup","stage":{"status":"","color":null,"score":0},"layer":"L2","state_validation":{"status":"ZK proofs","color":"white","score":3},"data_availability":{"status":"Onchain (SD)","color":"white","score":3},"exit_window":{"status":"None","color":"red","score":1},"sequencer_failure":{"status":"Enqueue via L1","color":"yellow","score":2},"proposer_failure":{"status":"Cannot withdraw","color":"yellow","score":2},"tvl":{"val":799790000.0,"str":"799.79 M","color":"green"},"checkmarks":2,"score":11},{"id":"funki","name":"Funki","type":"optimium","stage":{"status":"","color":null,"score":0},"layer":"L3","state_validation":{"status":null,"color":null,"score":0},"data_availability":{"status":null,"color":null,"score":0},"exit_window":{"status":null,"color":null,"score":0},"sequencer_failure":{"status":null,"color":null,"score":0},"proposer_failure":{"status":null,"color":null,"score":0},"tvl":{"val":3520.0,"str":"3.52 K","color":"red"},"checkmarks":0,"score":0},{"id":"mode","name":"Mode Network","type":"optimistic rollup","stage":{"status":"","color":null,"score":0},"layer":"L2","state_validation":{"status":"None","color":"red","score":1},"data_availability":{"status":"Onchain","color":"white","score":3},"exit_window":{"status":"None","color":"red","score":1},"sequencer_failure":{"status":"Self sequence","color":"white","score":3},"proposer_failure":{"status":"Cannot withdraw","color":"red","score":1},"tvl":{"val":375770000.0,"str":"375.77 M","color":"white"},"checkmarks":2,"score":9},{"id":"nal","name":"Nal","type":"optimistic rollup","stage":{"status":"","color":null,"score":0},"layer":"L2","state_validation":{"status":null,"color":null,"score":0},"data_availability":{"status":null,"color":null,"score":0},"exit_window":{"status":null,"color":null,"score":0},"sequencer_failure":{"status":null,"color":null,"score":0},"proposer_failure":{"status":null,"color":null,"score":0},"tvl":{"val":1060.0,"str":"1.06 K","color":"red"},"checkmarks":0,"score":0},{"id":"xai","name":"Xai","type":"optimium","stage":{"status":"n/a","color":"white","score":0},"layer":"L3","state_validation":{"status":"Fraud proofs (INT)","color":"red","score":1},"data_availability":{"status":"External (DAC)","color":"yellow","score":2},"exit_window":{"status":"None","color":"red","score":1},"sequencer_failure":{"status":"Self sequence","color":"white","score":3},"proposer_failure":{"status":"Self propose","color":"white","score":3},"tvl":{"val":1570000.0,"str":"1.57 M","color":"red"},"checkmarks":2,"score":10},{"id":"zkfair","name":"ZKFair","type":"validium","stage":{"status":"n/a","color":"white","score":0},"layer":"L2","state_validation":{"status":"ZK proofs (SN)","color":"white","score":3},"data_availability":{"status":"External (DAC)","color":"red","score":1},"exit_window":{"status":"None","color":"red","score":1},"sequencer_failure":{"status":"No mechanism","color":"red","score":1},"proposer_failure":{"status":"Self propose","color":"white","score":3},"tvl":{"val":17390000.0,"str":"17.39 M","color":"yellow"},"checkmarks":2,"score":9},{"id":"sxnetwork","name":"SX Network","type":"optimium","stage":{"status":"n/a","color":"white","score":0},"layer":"L3","state_validation":{"status":"Fraud proofs (INT)","color":"red","score":1},"data_availability":{"status":"External (DAC)","color":"red","score":1},"exit_window":{"status":"None","color":"red","score":1},"sequencer_failure":{"status":"Self sequence","color":"white","score":3},"proposer_failure":{"status":"Self propose","color":"white","score":3},"tvl":{"val":9280000.0,"str":"9.28 M","color":"yellow"},"checkmarks":2,"score":9},{"id":"hook","name":"Hook","type":"optimistic rollup","stage":{"status":"n/a","color":"white","score":0},"layer":"L2","state_validation":{"status":null,"color":null,"score":0},"data_availability":{"status":null,"color":null,"score":0},"exit_window":{"status":null,"color":null,"score":0},"sequencer_failure":{"status":null,"color":null,"score":0},"proposer_failure":{"status":null,"color":null,"score":0},"tvl":{"val":8430.0,"str":"8.43 K","color":"red"},"checkmarks":0,"score":0},{"id":"patex","name":"Patex Network","type":"optimistic rollup","stage":{"status":"","color":null,"score":0},"layer":"L2","state_validation":{"status":null,"color":null,"score":0},"data_availability":{"status":null,"color":null,"score":0},"exit_window":{"status":null,"color":null,"score":0},"sequencer_failure":{"status":null,"color":null,"score":0},"proposer_failure":{"status":null,"color":null,"score":0},"tvl":{"val":47650.0,"str":"47.65 K","color":"red"},"checkmarks":0,"score":0},{"id":"cartesi-honeypot","name":"Honeypot (Cartesi)","type":"optimistic rollup","stage":{"status":"","color":null,"score":0},"layer":"L2","state_validation":{"status":"None","color":"red","score":1},"data_availability":{"status":"Onchain","color":"white","score":3},"exit_window":{"status":"∞","color":"white","score":3},"sequencer_failure":{"status":"Self sequence","color":"white","score":3},"proposer_failure":{"status":"Cannot withdraw","color":"red","score":1},"tvl":{"val":223810.0,"str":"223.81 K","color":"red"},"checkmarks":3,"score":11},{"id":"ham","name":"Ham","type":"optimium","stage":{"status":"n/a","color":"white","score":0},"layer":"L3","state_validation":{"status":"None","color":"red","score":1},"data_availability":{"status":"External","color":"red","score":1},"exit_window":{"status":"None","color":"red","score":1},"sequencer_failure":{"status":"Self sequence","color":"white","score":3},"proposer_failure":{"status":"Cannot withdraw","color":"red","score":1},"tvl":{"val":127420.0,"str":"127.42 K","color":"red"},"checkmarks":1,"score":7},{"id":"ancient8","name":"Ancient8","type":"optimium","stage":{"status":"n/a","color":"white","score":0},"layer":"L3","state_validation":{"status":"None","color":"red","score":1},"data_availability":{"status":"External","color":"red","score":1},"exit_window":{"status":"None","color":"red","score":1},"sequencer_failure":{"status":"Self sequence","color":"white","score":3},"proposer_failure":{"status":"Cannot withdraw","color":"red","score":1},"tvl":{"val":1520000.0,"str":"1.52 M","color":"red"},"checkmarks":1,"score":7},{"id":"dbk","name":"DeBank Chain","type":"optimistic rollup","stage":{"status":"","color":null,"score":0},"layer":"L2","state_validation":{"status":"None","color":"red","score":1},"data_availability":{"status":"Onchain","color":"white","score":3},"exit_window":{"status":"None","color":"red","score":1},"sequencer_failure":{"status":"Self sequence","color":"white","score":3},"proposer_failure":{"status":"Cannot withdraw","color":"red","score":1},"tvl":{"val":644480.0,"str":"644.48 K","color":"red"},"checkmarks":2,"score":9},{"id":"karak","name":"Karak","type":"optimium","stage":{"status":"n/a","color":"white","score":0},"layer":"L3","state_validation":{"status":"None","color":"red","score":1},"data_availability":{"status":"External","color":"red","score":1},"exit_window":{"status":"None","color":"red","score":1},"sequencer_failure":{"status":"Self sequence","color":"white","score":3},"proposer_failure":{"status":"Cannot withdraw","color":"red","score":1},"tvl":{"val":28530000.0,"str":"28.53 M","color":"yellow"},"checkmarks":1,"score":7},{"id":"zircuit","name":"Zircuit","type":"optimistic rollup","stage":{"status":"","color":null,"score":0},"layer":"L2","state_validation":{"status":"None","color":"red","score":1},"data_availability":{"status":"Onchain","color":"white","score":3},"exit_window":{"status":"None","color":"red","score":1},"sequencer_failure":{"status":"Self sequence","color":"white","score":3},"proposer_failure":{"status":"Cannot withdraw","color":"red","score":1},"tvl":{"val":680530.0,"str":"680.53 K","color":"red"},"checkmarks":2,"score":9},{"id":"blast","name":"Blast","type":"optimistic rollup","stage":{"status":"","color":null,"score":0},"layer":"L2","state_validation":{"status":"None","color":"red","score":1},"data_availability":{"status":"Onchain","color":"white","score":3},"exit_window":{"status":"None","color":"red","score":1},"sequencer_failure":{"status":"Self sequence","color":"white","score":3},"proposer_failure":{"status":"Cannot withdraw","color":"red","score":1},"tvl":{"val":1390000000.0,"str":"1.39 B","color":"green"},"checkmarks":2,"score":9},{"id":"hypr","name":"Hypr","type":"optimium","stage":{"status":"n/a","color":"white","score":0},"layer":"L3","state_validation":{"status":"None","color":"red","score":1},"data_availability":{"status":"External","color":"red","score":1},"exit_window":{"status":"None","color":"red","score":1},"sequencer_failure":{"status":"Self sequence","color":"white","score":3},"proposer_failure":{"status":"Cannot withdraw","color":"red","score":1},"tvl":{"val":46220.0,"str":"46.22 K","color":"red"},"checkmarks":1,"score":7},{"id":"gpt","name":"GPT Protocol","type":"validium","stage":{"status":"n/a","color":"white","score":0},"layer":"L2","state_validation":{"status":"ZK proofs (SN)","color":"white","score":3},"data_availability":{"status":"External (DAC)","color":"red","score":1},"exit_window":{"status":"None","color":"red","score":1},"sequencer_failure":{"status":"No mechanism","color":"red","score":1},"proposer_failure":{"status":"Self propose","color":"white","score":3},"tvl":{"val":0,"str":"0","color":"red"},"checkmarks":2,"score":9},{"id":"pmon","name":"PMON Chain","type":"optimium","stage":{"status":"n/a","color":"white","score":0},"layer":"L3","state_validation":{"status":null,"color":null,"score":0},"data_availability":{"status":null,"color":null,"score":0},"exit_window":{"status":null,"color":null,"score":0},"sequencer_failure":{"status":null,"color":null,"score":0},"proposer_failure":{"status":null,"color":null,"score":0},"tvl":{"val":538.97,"str":"538.97","color":"red"},"checkmarks":0,"score":0},{"id":"arbitrum","name":"Arbitrum One","type":"optimistic rollup","stage":{"status":"","color":null,"score":0},"layer":"L2","state_validation":{"status":"Fraud proofs (INT)","color":"yellow","score":2},"data_availability":{"status":"Onchain","color":"white","score":3},"exit_window":{"status":"2d","color":"red","score":1},"sequencer_failure":{"status":"Self sequence","color":"white","score":3},"proposer_failure":{"status":"Self propose","color":"white","score":3},"tvl":{"val":12890000000.0,"str":"12.89 B","color":"green"},"checkmarks":3,"score":12},{"id":"silicon","name":"Silicon","type":"validium","stage":{"status":"n/a","color":"white","score":0},"layer":"L2","state_validation":{"status":"ZK proofs (SN)","color":"white","score":3},"data_availability":{"status":"External (DAC)","color":"red","score":1},"exit_window":{"status":"None","color":"red","score":1},"sequencer_failure":{"status":"No mechanism","color":"red","score":1},"proposer_failure":{"status":"Self propose","color":"white","score":3},"tvl":{"val":13050.0,"str":"13.05 K","color":"red"},"checkmarks":2,"score":9},{"id":"zkspace","name":"ZKSpace","type":"zk rollup","stage":{"status":"","color":null,"score":0},"layer":"L2","state_validation":{"status":"ZK proofs (SN)","color":"white","score":3},"data_availability":{"status":"Onchain","color":"white","score":3},"exit_window":{"status":"5d","color":"red","score":1},"sequencer_failure":{"status":"Force via L1","color":"white","score":3},"proposer_failure":{"status":"Use escape hatch","color":"white","score":3},"tvl":{"val":2440000.0,"str":"2.44 M","color":"red"},"checkmarks":4,"score":13},{"id":"bobanetwork","name":"Boba Network","type":"optimistic rollup","stage":{"status":"","color":null,"score":0},"layer":"L2","state_validation":{"status":"None","color":"red","score":1},"data_availability":{"status":"Onchain","color":"white","score":3},"exit_window":{"status":"None","color":"red","score":1},"sequencer_failure":{"status":"Self sequence","color":"white","score":3},"proposer_failure":{"status":"Cannot withdraw","color":"red","score":1},"tvl":{"val":11670000.0,"str":"11.67 M","color":"yellow"},"checkmarks":2,"score":9},{"id":"hychain","name":"HYCHAIN","type":"optimium","stage":{"status":"n/a","color":"white","score":0},"layer":"L3","state_validation":{"status":"Fraud proofs (INT)","color":"red","score":1},"data_availability":{"status":"External (DAC)","color":"red","score":1},"exit_window":{"status":"None","color":"red","score":1},"sequencer_failure":{"status":"Self sequence","color":"white","score":3},"proposer_failure":{"status":"Self propose","color":"white","score":3},"tvl":{"val":1100000.0,"str":"1.10 M","color":"red"},"checkmarks":2,"score":9},{"id":"metal","name":"Metal","type":"optimistic rollup","stage":{"status":"","color":null,"score":0},"layer":"L2","state_validation":{"status":"None","color":"red","score":1},"data_availability":{"status":"Onchain","color":"white","score":3},"exit_window":{"status":"None","color":"red","score":1},"sequencer_failure":{"status":"Self sequence","color":"white","score":3},"proposer_failure":{"status":"Cannot withdraw","color":"red","score":1},"tvl":{"val":156160.0,"str":"156.16 K","color":"red"},"checkmarks":2,"score":9},{"id":"edgeless","name":"Edgeless","type":"optimium","stage":{"status":"n/a","color":"white","score":0},"layer":"L3","state_validation":{"status":"Fraud proofs (INT)","color":"red","score":1},"data_availability":{"status":"External (DAC)","color":"red","score":1},"exit_window":{"status":"None","color":"red","score":1},"sequencer_failure":{"status":"Self sequence","color":"white","score":3},"proposer_failure":{"status":"Self propose","color":"white","score":3},"tvl":{"val":49200.0,"str":"49.20 K","color":"red"},"checkmarks":2,"score":9},{"id":"optimism","name":"OP Mainnet","type":"optimistic rollup","stage":{"status":"","color":null,"score":0},"layer":"L2","state_validation":{"status":"Fraud proofs (INT)","color":"white","score":3},"data_availability":{"status":"Onchain","color":"white","score":3},"exit_window":{"status":"None","color":"red","score":1},"sequencer_failure":{"status":"Self sequence","color":"white","score":3},"proposer_failure":{"status":"Self propose","color":"white","score":3},"tvl":{"val":5870000000.0,"str":"5.87 B","color":"green"},"checkmarks":4,"score":13},{"id":"fuelv1","name":"Fuel v1","type":"optimistic rollup","stage":{"status":"","color":null,"score":0},"layer":"L2","state_validation":{"status":"Fraud proofs (1R)","color":"white","score":3},"data_availability":{"status":"Onchain","color":"white","score":3},"exit_window":{"status":"∞","color":"white","score":3},"sequencer_failure":{"status":"Self sequence","color":"white","score":3},"proposer_failure":{"status":"Self propose","color":"white","score":3},"tvl":{"val":613.0,"str":"613.00","color":"red"},"checkmarks":5,"score":15},{"id":"derive","name":"Derive","type":"optimium","stage":{"status":"n/a","color":"white","score":0},"layer":"L3","state_validation":{"status":"None","color":"red","score":1},"data_availability":{"status":"External","color":"red","score":1},"exit_window":{"status":"None","color":"red","score":1},"sequencer_failure":{"status":"Self sequence","color":"white","score":3},"proposer_failure":{"status":"Cannot withdraw","color":"red","score":1},"tvl":{"val":48560000.0,"str":"48.56 M","color":"yellow"},"checkmarks":1,"score":7},{"id":"sanko","name":"Sanko","type":"optimium","stage":{"status":"n/a","color":"white","score":0},"layer":"L3","state_validation":{"status":"Fraud proofs (INT)","color":"red","score":1},"data_availability":{"status":"External (DAC)","color":"red","score":1},"exit_window":{"status":"None","color":"red","score":1},"sequencer_failure":{"status":"Self sequence","color":"white","score":3},"proposer_failure":{"status":"Self propose","color":"white","score":3},"tvl":{"val":17860000.0,"str":"17.86 M","color":"yellow"},"checkmarks":2,"score":9},{"id":"tanx","name":"tanX","type":"validium","stage":{"status":"n/a","color":"white","score":0},"layer":"L2","state_validation":{"status":"ZK proofs (ST)","color":"white","score":3},"data_availability":{"status":"External (DAC)","color":"red","score":1},"exit_window":{"status":"None","color":"red","score":1},"sequencer_failure":{"status":"Force via L1","color":"white","score":3},"proposer_failure":{"status":"Use escape hatch","color":"white","score":3},"tvl":{"val":1250000.0,"str":"1.25 M","color":"red"},"checkmarks":3,"score":11},{"id":"zora","name":"Zora","type":"optimistic rollup","stage":{"status":"","color":null,"score":0},"layer":"L2","state_validation":{"status":"None","color":"red","score":1},"data_availability":{"status":"Onchain","color":"white","score":3},"exit_window":{"status":"None","color":"red","score":1},"sequencer_failure":{"status":"Self sequence","color":"white","score":3},"proposer_failure":{"status":"Cannot withdraw","color":"red","score":1},"tvl":{"val":17860000.0,"str":"17.86 M","color":"yellow"},"checkmarks":2,"score":9},{"id":"swan","name":"Swan Chain","type":"optimistic rollup","stage":{"status":"","color":null,"score":0},"layer":"L2","state_validation":{"status":"None","color":"red","score":1},"data_availability":{"status":"Onchain","color":"white","score":3},"exit_window":{"status":"None","color":"red","score":1},"sequencer_failure":{"status":"Self sequence","color":"white","score":3},"proposer_failure":{"status":"Cannot withdraw","color":"red","score":1},"tvl":{"val":469310.0,"str":"469.31 K","color":"red"},"checkmarks":2,"score":9},{"id":"kroma","name":"Kroma","type":"optimistic rollup","stage":{"status":"","color":null,"score":0},"layer":"L2","state_validation":{"status":"Fraud proofs (INT, ZK)","color":"red","score":1},"data_availability":{"status":"Onchain","color":"white","score":3},"exit_window":{"status":"None","color":"red","score":1},"sequencer_failure":{"status":"Self sequence","color":"white","score":3},"proposer_failure":{"status":"Self propose","color":"white","score":3},"tvl":{"val":16970000.0,"str":"16.97 M","color":"yellow"},"checkmarks":3,"score":11},{"id":"apex","name":"ApeX","type":"validium","stage":{"status":"n/a","color":"white","score":0},"layer":"L2","state_validation":{"status":"ZK proofs (ST)","color":"white","score":3},"data_availability":{"status":"External (DAC)","color":"red","score":1},"exit_window":{"status":"None","color":"red","score":1},"sequencer_failure":{"status":"Force via L1","color":"white","score":3},"proposer_failure":{"status":"Use escape hatch","color":"white","score":3},"tvl":{"val":85070000.0,"str":"85.07 M","color":"yellow"},"checkmarks":3,"score":11},{"id":"donatuz","name":"Donatuz","type":"optimium","stage":{"status":"n/a","color":"white","score":0},"layer":"L3","state_validation":{"status":null,"color":null,"score":0},"data_availability":{"status":null,"color":null,"score":0},"exit_window":{"status":null,"color":null,"score":0},"sequencer_failure":{"status":null,"color":null,"score":0},"proposer_failure":{"status":null,"color":null,"score":0},"tvl":{"val":1200.0,"str":"1.20 K","color":"red"},"checkmarks":0,"score":0}]}